irisflower
