Metadata-Version: 1.1
Name: irisflower
Version: 1.0.2
Summary: Iris flower species classifier
Home-page: https://github.com/risan/iris-flower-classifier
Author: Risan Bagja Pradana
Author-email: risanbagja@gmail.com
License: MIT
Keywords: machine learning classifier
Platform: UNKNOWN
Classifier: Development Status :: 3 - Alpha
Classifier: Intended Audience :: Developers
Classifier: Intended Audience :: Education
Classifier: Topic :: Scientific/Engineering :: Information Analysis
Classifier: License :: OSI Approved :: MIT License
Classifier: Programming Language :: Python :: 2.6
Classifier: Programming Language :: Python :: 2.7
Classifier: Programming Language :: Python :: 3
Classifier: Programming Language :: Python :: 3.3
Classifier: Programming Language :: Python :: 3.4
Classifier: Programming Language :: Python :: 3.5
